<Properties StartupConfiguration="{3E89751E-8CF2-4EB7-87AB-10267E25C974}|Default">
  <MonoDevelop.Ide.ItemProperties.CustomSample PreferredExecutionTarget="MonoDevelop.Default" />
  <MonoDevelop.Ide.Workbench ActiveDocument="UnitTest1.cs">
    <Files>
      <File FileName="MySmartContract.cs" Line="1" Column="1" />
      <File FileName="UnitTest1.cs" Line="6" Column="28" />
    </Files>
    <Pads>
      <Pad Id="MonoDevelop.UnitTesting.TestPad">
        <State name="__root__">
          <Node name="CustomSample" expanded="True">
            <Node name="CustomSample" selected="True" />
          </Node>
        </State>
      </Pad>
    </Pads>
  </MonoDevelop.Ide.Workbench>
  <MonoDevelop.Ide.Workspace ActiveConfiguration="Debug" />
  <MonoDevelop.Ide.DebuggingService.Breakpoints>
    <BreakpointStore />
  </MonoDevelop.Ide.DebuggingService.Breakpoints>
  <MonoDevelop.Ide.DebuggingService.PinnedWatches />
  <MultiItemStartupConfigurations />
</Properties>